cli/__init__.py
cli/palantir.py
cli/__pycache__/__init__.cpython-37.pyc
cli/__pycache__/palantir.cpython-37.pyc
cli/defaultfiles/callback.py
cli/defaultfiles/config.yml
cli/defaultfiles/palantir.txt
crawler/__init__.py
crawler/preprocess.py
crawler/scrape.py
palantir/__init__.py
palantir/aggregators.py
palantir/params.py
palantir/predictors.py
palantir/preprocessor.py
palantir/utils.py
simulator/__init__.py
simulator/default.py
simulator/sim.py
palantir_cli-0.0.1.dist-info/LICENSE
palantir_cli-0.0.1.dist-info/METADATA
palantir_cli-0.0.1.dist-info/WHEEL
palantir_cli-0.0.1.dist-info/entry_points.txt
palantir_cli-0.0.1.dist-info/top_level.txt
palantir_cli-0.0.1.dist-info/RECORD
