Metadata-Version: 2.1
Name: palantir-cli
Version: 0.0.1
Summary: security analyzer and predictor
Home-page: https://github.com/nathanielCherian/palantir
Author: Nathaniel Cherian
Author-email: nathaniel@sylica.com
License: MIT
Platform: UNKNOWN
Classifier: Programming Language :: Python :: 3
Classifier: Development Status :: 3 - Alpha
Classifier: License :: OSI Approved :: MIT License
Classifier: Operating System :: OS Independent
Requires-Python: >=3.6
Requires-Dist: numpy
Requires-Dist: pandas
Requires-Dist: scikit-learn
Requires-Dist: finta
Requires-Dist: prompt-toolkit
Requires-Dist: pyyaml
